{"v":"5.6.10","fr":30,"ip":0,"op":59,"w":375,"h":798,"nm":"Comp 4","ddd":0,"assets":[],"layers":[{"ddd":0,"ind":1,"ty":4,"nm":"Shape Layer 10","sr":1,"ks":{"o":{"a":1,"k":[{"i":{"x":[0.833],"y":[0.833]},"o":{"x":[0.167],"y":[0.167]},"t":0,"s":[0]},{"i":{"x":[0.833],"y":[0.833]},"o":{"x":[0.167],"y":[0.167]},"t":4,"s":[100]},{"i":{"x":[0.833],"y":[0.833]},"o":{"x":[0.167],"y":[0.167]},"t":15,"s":[100]},{"t":19,"s":[0]}],"ix":11},"r":{"a":0,"k":0,"ix":10},"p":{"a":0,"k":[350,396.571,0],"ix":2},"a":{"a":0,"k":[0,0,0],"ix":1},"s":{"a":0,"k":[100,95.15,100],"ix":6}},"ao":0,"sy":[{"c":{"a":0,"k":[0,0,0,1],"ix":2},"o":{"a":0,"k":75,"ix":3},"a":{"a":0,"k":120,"ix":5},"s":{"a":0,"k":5,"ix":8},"d":{"a":0,"k":5,"ix":6},"ch":{"a":0,"k":0,"ix":7},"bm":{"a":0,"k":5,"ix":1},"no":{"a":0,"k":0,"ix":9},"lc":{"a":0,"k":1,"ix":10},"ty":1,"nm":"Drop Shadow"},{"c":{"a":0,"k":[0,0,0,1],"ix":2},"o":{"a":0,"k":75,"ix":3},"a":{"a":0,"k":120,"ix":5},"s":{"a":0,"k":5,"ix":8},"d":{"a":0,"k":5,"ix":6},"ch":{"a":0,"k":0,"ix":7},"bm":{"a":0,"k":5,"ix":1},"no":{"a":0,"k":0,"ix":9},"ty":2,"nm":"Inner Shadow"},{"c":{"a":0,"k":[1,1,0.745098039216,1],"ix":5},"o":{"a":0,"k":75,"ix":2},"s":{"a":0,"k":5,"ix":10},"r":{"a":0,"k":50,"ix":11},"ch":{"a":0,"k":0,"ix":9},"bm":{"a":0,"k":11,"ix":1},"no":{"a":0,"k":0,"ix":3},"j":{"a":0,"k":0,"ix":12},"ty":3,"nm":"Outer Glow"},{"c":{"a":0,"k":[1,1,0.745098039216,1],"ix":5},"o":{"a":0,"k":75,"ix":2},"s":{"a":0,"k":5,"ix":11},"r":{"a":0,"k":50,"ix":12},"sr":{"a":0,"k":1,"ix":9},"ch":{"a":0,"k":0,"ix":10},"bm":{"a":0,"k":11,"ix":1},"no":{"a":0,"k":0,"ix":3},"j":{"a":0,"k":0,"ix":13},"ty":4,"nm":"Inner Glow"},{"c":{"a":0,"k":[1,0,0,1],"ix":2},"s":{"a":0,"k":3,"ix":3},"ty":0,"nm":"Stroke"}],"shapes":[{"ty":"gr","it":[{"ty":"rc","d":1,"s":{"a":0,"k":[5.5,64.5],"ix":2},"p":{"a":0,"k":[0,0],"ix":3},"r":{"a":0,"k":0,"ix":4},"nm":"Rectangle Path 1","mn":"ADBE Vector Shape - Rect","hd":false},{"ty":"fl","c":{"a":0,"k":[0.733333333333,0.458823529412,0.466666666667,1],"ix":4},"o":{"a":0,"k":100,"ix":5},"r":1,"bm":1,"nm":"Fill 1","mn":"ADBE Vector Graphic - Fill","hd":false},{"ty":"tr","p":{"a":0,"k":[-72.5,-8.75],"ix":2},"a":{"a":0,"k":[0,0],"ix":1},"s":{"a":0,"k":[100,107.049],"ix":3},"r":{"a":0,"k":0,"ix":6},"o":{"a":0,"k":100,"ix":7},"sk":{"a":0,"k":0,"ix":4},"sa":{"a":0,"k":0,"ix":5},"nm":"Transform"}],"nm":"Rectangle 1","np":3,"cix":2,"bm":0,"ix":1,"mn":"ADBE Vector Group","hd":false}],"ip":0,"op":300,"st":0,"bm":0},{"ddd":0,"ind":2,"ty":4,"nm":"Shape Layer 17","sr":1,"ks":{"o":{"a":1,"k":[{"i":{"x":[0.833],"y":[0.833]},"o":{"x":[0.167],"y":[0.167]},"t":4,"s":[0]},{"i":{"x":[0.833],"y":[0.833]},"o":{"x":[0.167],"y":[0.167]},"t":8,"s":[100]},{"i":{"x":[0.833],"y":[0.833]},"o":{"x":[0.167],"y":[0.167]},"t":19,"s":[100]},{"t":23,"s":[0]}],"ix":11},"r":{"a":0,"k":0,"ix":10},"p":{"a":0,"k":[338.781,397.411,0],"ix":2},"a":{"a":0,"k":[0,0,0],"ix":1},"s":{"a":0,"k":[100,97.09,100],"ix":6}},"ao":0,"sy":[{"c":{"a":0,"k":[0,0,0,1],"ix":2},"o":{"a":0,"k":75,"ix":3},"a":{"a":0,"k":120,"ix":5},"s":{"a":0,"k":5,"ix":8},"d":{"a":0,"k":5,"ix":6},"ch":{"a":0,"k":0,"ix":7},"bm":{"a":0,"k":5,"ix":1},"no":{"a":0,"k":0,"ix":9},"lc":{"a":0,"k":1,"ix":10},"ty":1,"nm":"Drop Shadow"},{"c":{"a":0,"k":[0,0,0,1],"ix":2},"o":{"a":0,"k":75,"ix":3},"a":{"a":0,"k":120,"ix":5},"s":{"a":0,"k":5,"ix":8},"d":{"a":0,"k":5,"ix":6},"ch":{"a":0,"k":0,"ix":7},"bm":{"a":0,"k":5,"ix":1},"no":{"a":0,"k":0,"ix":9},"ty":2,"nm":"Inner Shadow"},{"c":{"a":0,"k":[1,1,0.745098039216,1],"ix":5},"o":{"a":0,"k":75,"ix":2},"s":{"a":0,"k":5,"ix":10},"r":{"a":0,"k":50,"ix":11},"ch":{"a":0,"k":0,"ix":9},"bm":{"a":0,"k":11,"ix":1},"no":{"a":0,"k":0,"ix":3},"j":{"a":0,"k":0,"ix":12},"ty":3,"nm":"Outer Glow"},{"c":{"a":0,"k":[1,1,0.745098039216,1],"ix":5},"o":{"a":0,"k":75,"ix":2},"s":{"a":0,"k":5,"ix":11},"r":{"a":0,"k":50,"ix":12},"sr":{"a":0,"k":1,"ix":9},"ch":{"a":0,"k":0,"ix":10},"bm":{"a":0,"k":11,"ix":1},"no":{"a":0,"k":0,"ix":3},"j":{"a":0,"k":0,"ix":13},"ty":4,"nm":"Inner Glow"},{"c":{"a":0,"k":[1,0,0,1],"ix":2},"s":{"a":0,"k":3,"ix":3},"ty":0,"nm":"Stroke"}],"shapes":[{"ty":"gr","it":[{"ty":"rc","d":1,"s":{"a":0,"k":[5.5,64.5],"ix":2},"p":{"a":0,"k":[0,0],"ix":3},"r":{"a":0,"k":0,"ix":4},"nm":"Rectangle Path 1","mn":"ADBE Vector Shape - Rect","hd":false},{"ty":"fl","c":{"a":0,"k":[0.733333333333,0.458823529412,0.466666666667,1],"ix":4},"o":{"a":0,"k":100,"ix":5},"r":1,"bm":1,"nm":"Fill 1","mn":"ADBE Vector Graphic - Fill","hd":false},{"ty":"tr","p":{"a":0,"k":[-72.5,-8.75],"ix":2},"a":{"a":0,"k":[0,0],"ix":1},"s":{"a":0,"k":[100,107.049],"ix":3},"r":{"a":0,"k":0,"ix":6},"o":{"a":0,"k":100,"ix":7},"sk":{"a":0,"k":0,"ix":4},"sa":{"a":0,"k":0,"ix":5},"nm":"Transform"}],"nm":"Rectangle 1","np":3,"cix":2,"bm":0,"ix":1,"mn":"ADBE Vector Group","hd":false}],"ip":0,"op":300,"st":0,"bm":0},{"ddd":0,"ind":3,"ty":4,"nm":"Shape Layer 16","sr":1,"ks":{"o":{"a":1,"k":[{"i":{"x":[0.833],"y":[0.833]},"o":{"x":[0.167],"y":[0.167]},"t":8,"s":[0]},{"i":{"x":[0.833],"y":[0.833]},"o":{"x":[0.167],"y":[0.167]},"t":12,"s":[100]},{"i":{"x":[0.833],"y":[0.833]},"o":{"x":[0.167],"y":[0.167]},"t":23,"s":[100]},{"t":27,"s":[0]}],"ix":11},"r":{"a":0,"k":0,"ix":10},"p":{"a":0,"k":[327.563,399.509,0],"ix":2},"a":{"a":0,"k":[0,0,0],"ix":1},"s":{"a":0,"k":[100,101.94,100],"ix":6}},"ao":0,"sy":[{"c":{"a":0,"k":[0,0,0,1],"ix":2},"o":{"a":0,"k":75,"ix":3},"a":{"a":0,"k":120,"ix":5},"s":{"a":0,"k":5,"ix":8},"d":{"a":0,"k":5,"ix":6},"ch":{"a":0,"k":0,"ix":7},"bm":{"a":0,"k":5,"ix":1},"no":{"a":0,"k":0,"ix":9},"lc":{"a":0,"k":1,"ix":10},"ty":1,"nm":"Drop Shadow"},{"c":{"a":0,"k":[0,0,0,1],"ix":2},"o":{"a":0,"k":75,"ix":3},"a":{"a":0,"k":120,"ix":5},"s":{"a":0,"k":5,"ix":8},"d":{"a":0,"k":5,"ix":6},"ch":{"a":0,"k":0,"ix":7},"bm":{"a":0,"k":5,"ix":1},"no":{"a":0,"k":0,"ix":9},"ty":2,"nm":"Inner Shadow"},{"c":{"a":0,"k":[1,1,0.745098039216,1],"ix":5},"o":{"a":0,"k":75,"ix":2},"s":{"a":0,"k":5,"ix":10},"r":{"a":0,"k":50,"ix":11},"ch":{"a":0,"k":0,"ix":9},"bm":{"a":0,"k":11,"ix":1},"no":{"a":0,"k":0,"ix":3},"j":{"a":0,"k":0,"ix":12},"ty":3,"nm":"Outer Glow"},{"c":{"a":0,"k":[1,1,0.745098039216,1],"ix":5},"o":{"a":0,"k":75,"ix":2},"s":{"a":0,"k":5,"ix":11},"r":{"a":0,"k":50,"ix":12},"sr":{"a":0,"k":1,"ix":9},"ch":{"a":0,"k":0,"ix":10},"bm":{"a":0,"k":11,"ix":1},"no":{"a":0,"k":0,"ix":3},"j":{"a":0,"k":0,"ix":13},"ty":4,"nm":"Inner Glow"},{"c":{"a":0,"k":[1,0,0,1],"ix":2},"s":{"a":0,"k":3,"ix":3},"ty":0,"nm":"Stroke"}],"shapes":[{"ty":"gr","it":[{"ty":"rc","d":1,"s":{"a":0,"k":[5.5,64.5],"ix":2},"p":{"a":0,"k":[0,0],"ix":3},"r":{"a":0,"k":0,"ix":4},"nm":"Rectangle Path 1","mn":"ADBE Vector Shape - Rect","hd":false},{"ty":"fl","c":{"a":0,"k":[0.733333333333,0.458823529412,0.466666666667,1],"ix":4},"o":{"a":0,"k":100,"ix":5},"r":1,"bm":1,"nm":"Fill 1","mn":"ADBE Vector Graphic - Fill","hd":false},{"ty":"tr","p":{"a":0,"k":[-72.5,-8.75],"ix":2},"a":{"a":0,"k":[0,0],"ix":1},"s":{"a":0,"k":[100,107.049],"ix":3},"r":{"a":0,"k":0,"ix":6},"o":{"a":0,"k":100,"ix":7},"sk":{"a":0,"k":0,"ix":4},"sa":{"a":0,"k":0,"ix":5},"nm":"Transform"}],"nm":"Rectangle 1","np":3,"cix":2,"bm":0,"ix":1,"mn":"ADBE Vector Group","hd":false}],"ip":0,"op":300,"st":0,"bm":0},{"ddd":0,"ind":4,"ty":4,"nm":"Shape Layer 15","sr":1,"ks":{"o":{"a":1,"k":[{"i":{"x":[0.833],"y":[0.833]},"o":{"x":[0.167],"y":[0.167]},"t":12,"s":[0]},{"i":{"x":[0.833],"y":[0.833]},"o":{"x":[0.167],"y":[0.167]},"t":16,"s":[100]},{"i":{"x":[0.833],"y":[0.833]},"o":{"x":[0.167],"y":[0.167]},"t":27,"s":[100]},{"t":31,"s":[0]}],"ix":11},"r":{"a":0,"k":0,"ix":10},"p":{"a":0,"k":[316.344,401.188,0],"ix":2},"a":{"a":0,"k":[0,0,0],"ix":1},"s":{"a":0,"k":[100,105.82,100],"ix":6}},"ao":0,"sy":[{"c":{"a":0,"k":[0,0,0,1],"ix":2},"o":{"a":0,"k":75,"ix":3},"a":{"a":0,"k":120,"ix":5},"s":{"a":0,"k":5,"ix":8},"d":{"a":0,"k":5,"ix":6},"ch":{"a":0,"k":0,"ix":7},"bm":{"a":0,"k":5,"ix":1},"no":{"a":0,"k":0,"ix":9},"lc":{"a":0,"k":1,"ix":10},"ty":1,"nm":"Drop Shadow"},{"c":{"a":0,"k":[0,0,0,1],"ix":2},"o":{"a":0,"k":75,"ix":3},"a":{"a":0,"k":120,"ix":5},"s":{"a":0,"k":5,"ix":8},"d":{"a":0,"k":5,"ix":6},"ch":{"a":0,"k":0,"ix":7},"bm":{"a":0,"k":5,"ix":1},"no":{"a":0,"k":0,"ix":9},"ty":2,"nm":"Inner Shadow"},{"c":{"a":0,"k":[1,1,0.745098039216,1],"ix":5},"o":{"a":0,"k":75,"ix":2},"s":{"a":0,"k":5,"ix":10},"r":{"a":0,"k":50,"ix":11},"ch":{"a":0,"k":0,"ix":9},"bm":{"a":0,"k":11,"ix":1},"no":{"a":0,"k":0,"ix":3},"j":{"a":0,"k":0,"ix":12},"ty":3,"nm":"Outer Glow"},{"c":{"a":0,"k":[1,1,0.745098039216,1],"ix":5},"o":{"a":0,"k":75,"ix":2},"s":{"a":0,"k":5,"ix":11},"r":{"a":0,"k":50,"ix":12},"sr":{"a":0,"k":1,"ix":9},"ch":{"a":0,"k":0,"ix":10},"bm":{"a":0,"k":11,"ix":1},"no":{"a":0,"k":0,"ix":3},"j":{"a":0,"k":0,"ix":13},"ty":4,"nm":"Inner Glow"},{"c":{"a":0,"k":[1,0,0,1],"ix":2},"s":{"a":0,"k":3,"ix":3},"ty":0,"nm":"Stroke"}],"shapes":[{"ty":"gr","it":[{"ty":"rc","d":1,"s":{"a":0,"k":[5.5,64.5],"ix":2},"p":{"a":0,"k":[0,0],"ix":3},"r":{"a":0,"k":0,"ix":4},"nm":"Rectangle Path 1","mn":"ADBE Vector Shape - Rect","hd":false},{"ty":"fl","c":{"a":0,"k":[0.733333333333,0.458823529412,0.466666666667,1],"ix":4},"o":{"a":0,"k":100,"ix":5},"r":1,"bm":1,"nm":"Fill 1","mn":"ADBE Vector Graphic - Fill","hd":false},{"ty":"tr","p":{"a":0,"k":[-72.5,-8.75],"ix":2},"a":{"a":0,"k":[0,0],"ix":1},"s":{"a":0,"k":[100,107.049],"ix":3},"r":{"a":0,"k":0,"ix":6},"o":{"a":0,"k":100,"ix":7},"sk":{"a":0,"k":0,"ix":4},"sa":{"a":0,"k":0,"ix":5},"nm":"Transform"}],"nm":"Rectangle 1","np":3,"cix":2,"bm":0,"ix":1,"mn":"ADBE Vector Group","hd":false}],"ip":0,"op":300,"st":0,"bm":0},{"ddd":0,"ind":5,"ty":4,"nm":"Shape Layer 14","sr":1,"ks":{"o":{"a":1,"k":[{"i":{"x":[0.833],"y":[0.833]},"o":{"x":[0.167],"y":[0.167]},"t":16,"s":[0]},{"i":{"x":[0.833],"y":[0.833]},"o":{"x":[0.167],"y":[0.167]},"t":20,"s":[100]},{"i":{"x":[0.833],"y":[0.833]},"o":{"x":[0.167],"y":[0.167]},"t":31,"s":[100]},{"t":35,"s":[0]}],"ix":11},"r":{"a":0,"k":0,"ix":10},"p":{"a":0,"k":[305.125,402.447,0],"ix":2},"a":{"a":0,"k":[0,0,0],"ix":1},"s":{"a":0,"k":[100,108.73,100],"ix":6}},"ao":0,"sy":[{"c":{"a":0,"k":[0,0,0,1],"ix":2},"o":{"a":0,"k":75,"ix":3},"a":{"a":0,"k":120,"ix":5},"s":{"a":0,"k":5,"ix":8},"d":{"a":0,"k":5,"ix":6},"ch":{"a":0,"k":0,"ix":7},"bm":{"a":0,"k":5,"ix":1},"no":{"a":0,"k":0,"ix":9},"lc":{"a":0,"k":1,"ix":10},"ty":1,"nm":"Drop Shadow"},{"c":{"a":0,"k":[0,0,0,1],"ix":2},"o":{"a":0,"k":75,"ix":3},"a":{"a":0,"k":120,"ix":5},"s":{"a":0,"k":5,"ix":8},"d":{"a":0,"k":5,"ix":6},"ch":{"a":0,"k":0,"ix":7},"bm":{"a":0,"k":5,"ix":1},"no":{"a":0,"k":0,"ix":9},"ty":2,"nm":"Inner Shadow"},{"c":{"a":0,"k":[1,1,0.745098039216,1],"ix":5},"o":{"a":0,"k":75,"ix":2},"s":{"a":0,"k":5,"ix":10},"r":{"a":0,"k":50,"ix":11},"ch":{"a":0,"k":0,"ix":9},"bm":{"a":0,"k":11,"ix":1},"no":{"a":0,"k":0,"ix":3},"j":{"a":0,"k":0,"ix":12},"ty":3,"nm":"Outer Glow"},{"c":{"a":0,"k":[1,1,0.745098039216,1],"ix":5},"o":{"a":0,"k":75,"ix":2},"s":{"a":0,"k":5,"ix":11},"r":{"a":0,"k":50,"ix":12},"sr":{"a":0,"k":1,"ix":9},"ch":{"a":0,"k":0,"ix":10},"bm":{"a":0,"k":11,"ix":1},"no":{"a":0,"k":0,"ix":3},"j":{"a":0,"k":0,"ix":13},"ty":4,"nm":"Inner Glow"},{"c":{"a":0,"k":[1,0,0,1],"ix":2},"s":{"a":0,"k":3,"ix":3},"ty":0,"nm":"Stroke"}],"shapes":[{"ty":"gr","it":[{"ty":"rc","d":1,"s":{"a":0,"k":[5.5,64.5],"ix":2},"p":{"a":0,"k":[0,0],"ix":3},"r":{"a":0,"k":0,"ix":4},"nm":"Rectangle Path 1","mn":"ADBE Vector Shape - Rect","hd":false},{"ty":"fl","c":{"a":0,"k":[0.733333333333,0.458823529412,0.466666666667,1],"ix":4},"o":{"a":0,"k":100,"ix":5},"r":1,"bm":1,"nm":"Fill 1","mn":"ADBE Vector Graphic - Fill","hd":false},{"ty":"tr","p":{"a":0,"k":[-72.5,-8.75],"ix":2},"a":{"a":0,"k":[0,0],"ix":1},"s":{"a":0,"k":[100,107.049],"ix":3},"r":{"a":0,"k":0,"ix":6},"o":{"a":0,"k":100,"ix":7},"sk":{"a":0,"k":0,"ix":4},"sa":{"a":0,"k":0,"ix":5},"nm":"Transform"}],"nm":"Rectangle 1","np":3,"cix":2,"bm":0,"ix":1,"mn":"ADBE Vector Group","hd":false}],"ip":0,"op":300,"st":0,"bm":0},{"ddd":0,"ind":6,"ty":4,"nm":"Shape Layer 13","sr":1,"ks":{"o":{"a":1,"k":[{"i":{"x":[0.833],"y":[0.833]},"o":{"x":[0.167],"y":[0.167]},"t":20,"s":[0]},{"i":{"x":[0.833],"y":[0.833]},"o":{"x":[0.167],"y":[0.167]},"t":24,"s":[100]},{"i":{"x":[0.833],"y":[0.833]},"o":{"x":[0.167],"y":[0.167]},"t":35,"s":[100]},{"t":39,"s":[0]}],"ix":11},"r":{"a":0,"k":0,"ix":10},"p":{"a":0,"k":[293.906,403.707,0],"ix":2},"a":{"a":0,"k":[0,0,0],"ix":1},"s":{"a":0,"k":[100,111.64,100],"ix":6}},"ao":0,"sy":[{"c":{"a":0,"k":[0,0,0,1],"ix":2},"o":{"a":0,"k":75,"ix":3},"a":{"a":0,"k":120,"ix":5},"s":{"a":0,"k":5,"ix":8},"d":{"a":0,"k":5,"ix":6},"ch":{"a":0,"k":0,"ix":7},"bm":{"a":0,"k":5,"ix":1},"no":{"a":0,"k":0,"ix":9},"lc":{"a":0,"k":1,"ix":10},"ty":1,"nm":"Drop Shadow"},{"c":{"a":0,"k":[0,0,0,1],"ix":2},"o":{"a":0,"k":75,"ix":3},"a":{"a":0,"k":120,"ix":5},"s":{"a":0,"k":5,"ix":8},"d":{"a":0,"k":5,"ix":6},"ch":{"a":0,"k":0,"ix":7},"bm":{"a":0,"k":5,"ix":1},"no":{"a":0,"k":0,"ix":9},"ty":2,"nm":"Inner Shadow"},{"c":{"a":0,"k":[1,1,0.745098039216,1],"ix":5},"o":{"a":0,"k":75,"ix":2},"s":{"a":0,"k":5,"ix":10},"r":{"a":0,"k":50,"ix":11},"ch":{"a":0,"k":0,"ix":9},"bm":{"a":0,"k":11,"ix":1},"no":{"a":0,"k":0,"ix":3},"j":{"a":0,"k":0,"ix":12},"ty":3,"nm":"Outer Glow"},{"c":{"a":0,"k":[1,1,0.745098039216,1],"ix":5},"o":{"a":0,"k":75,"ix":2},"s":{"a":0,"k":5,"ix":11},"r":{"a":0,"k":50,"ix":12},"sr":{"a":0,"k":1,"ix":9},"ch":{"a":0,"k":0,"ix":10},"bm":{"a":0,"k":11,"ix":1},"no":{"a":0,"k":0,"ix":3},"j":{"a":0,"k":0,"ix":13},"ty":4,"nm":"Inner Glow"},{"c":{"a":0,"k":[1,0,0,1],"ix":2},"s":{"a":0,"k":3,"ix":3},"ty":0,"nm":"Stroke"}],"shapes":[{"ty":"gr","it":[{"ty":"rc","d":1,"s":{"a":0,"k":[5.5,64.5],"ix":2},"p":{"a":0,"k":[0,0],"ix":3},"r":{"a":0,"k":0,"ix":4},"nm":"Rectangle Path 1","mn":"ADBE Vector Shape - Rect","hd":false},{"ty":"fl","c":{"a":0,"k":[0.733333333333,0.458823529412,0.466666666667,1],"ix":4},"o":{"a":0,"k":100,"ix":5},"r":1,"bm":1,"nm":"Fill 1","mn":"ADBE Vector Graphic - Fill","hd":false},{"ty":"tr","p":{"a":0,"k":[-72.5,-8.75],"ix":2},"a":{"a":0,"k":[0,0],"ix":1},"s":{"a":0,"k":[100,107.049],"ix":3},"r":{"a":0,"k":0,"ix":6},"o":{"a":0,"k":100,"ix":7},"sk":{"a":0,"k":0,"ix":4},"sa":{"a":0,"k":0,"ix":5},"nm":"Transform"}],"nm":"Rectangle 1","np":3,"cix":2,"bm":0,"ix":1,"mn":"ADBE Vector Group","hd":false}],"ip":0,"op":300,"st":0,"bm":0},{"ddd":0,"ind":7,"ty":4,"nm":"Shape Layer 12","sr":1,"ks":{"o":{"a":1,"k":[{"i":{"x":[0.833],"y":[0.833]},"o":{"x":[0.167],"y":[0.167]},"t":24,"s":[0]},{"i":{"x":[0.833],"y":[0.833]},"o":{"x":[0.167],"y":[0.167]},"t":28,"s":[100]},{"i":{"x":[0.833],"y":[0.833]},"o":{"x":[0.167],"y":[0.167]},"t":39,"s":[100]},{"t":43,"s":[0]}],"ix":11},"r":{"a":0,"k":0,"ix":10},"p":{"a":0,"k":[282.688,405.805,0],"ix":2},"a":{"a":0,"k":[0,0,0],"ix":1},"s":{"a":0,"k":[100,116.49,100],"ix":6}},"ao":0,"sy":[{"c":{"a":0,"k":[0,0,0,1],"ix":2},"o":{"a":0,"k":75,"ix":3},"a":{"a":0,"k":120,"ix":5},"s":{"a":0,"k":5,"ix":8},"d":{"a":0,"k":5,"ix":6},"ch":{"a":0,"k":0,"ix":7},"bm":{"a":0,"k":5,"ix":1},"no":{"a":0,"k":0,"ix":9},"lc":{"a":0,"k":1,"ix":10},"ty":1,"nm":"Drop Shadow"},{"c":{"a":0,"k":[0,0,0,1],"ix":2},"o":{"a":0,"k":75,"ix":3},"a":{"a":0,"k":120,"ix":5},"s":{"a":0,"k":5,"ix":8},"d":{"a":0,"k":5,"ix":6},"ch":{"a":0,"k":0,"ix":7},"bm":{"a":0,"k":5,"ix":1},"no":{"a":0,"k":0,"ix":9},"ty":2,"nm":"Inner Shadow"},{"c":{"a":0,"k":[1,1,0.745098039216,1],"ix":5},"o":{"a":0,"k":75,"ix":2},"s":{"a":0,"k":5,"ix":10},"r":{"a":0,"k":50,"ix":11},"ch":{"a":0,"k":0,"ix":9},"bm":{"a":0,"k":11,"ix":1},"no":{"a":0,"k":0,"ix":3},"j":{"a":0,"k":0,"ix":12},"ty":3,"nm":"Outer Glow"},{"c":{"a":0,"k":[1,1,0.745098039216,1],"ix":5},"o":{"a":0,"k":75,"ix":2},"s":{"a":0,"k":5,"ix":11},"r":{"a":0,"k":50,"ix":12},"sr":{"a":0,"k":1,"ix":9},"ch":{"a":0,"k":0,"ix":10},"bm":{"a":0,"k":11,"ix":1},"no":{"a":0,"k":0,"ix":3},"j":{"a":0,"k":0,"ix":13},"ty":4,"nm":"Inner Glow"},{"c":{"a":0,"k":[1,0,0,1],"ix":2},"s":{"a":0,"k":3,"ix":3},"ty":0,"nm":"Stroke"}],"shapes":[{"ty":"gr","it":[{"ty":"rc","d":1,"s":{"a":0,"k":[5.5,64.5],"ix":2},"p":{"a":0,"k":[0,0],"ix":3},"r":{"a":0,"k":0,"ix":4},"nm":"Rectangle Path 1","mn":"ADBE Vector Shape - Rect","hd":false},{"ty":"fl","c":{"a":0,"k":[0.721568627451,0.376470588235,0.38431372549,1],"ix":4},"o":{"a":0,"k":100,"ix":5},"r":1,"bm":1,"nm":"Fill 1","mn":"ADBE Vector Graphic - Fill","hd":false},{"ty":"tr","p":{"a":0,"k":[-72.5,-8.75],"ix":2},"a":{"a":0,"k":[0,0],"ix":1},"s":{"a":0,"k":[100,107.049],"ix":3},"r":{"a":0,"k":0,"ix":6},"o":{"a":0,"k":100,"ix":7},"sk":{"a":0,"k":0,"ix":4},"sa":{"a":0,"k":0,"ix":5},"nm":"Transform"}],"nm":"Rectangle 1","np":3,"cix":2,"bm":0,"ix":1,"mn":"ADBE Vector Group","hd":false}],"ip":0,"op":300,"st":0,"bm":0},{"ddd":0,"ind":8,"ty":4,"nm":"Shape Layer 11","sr":1,"ks":{"o":{"a":1,"k":[{"i":{"x":[0.833],"y":[0.833]},"o":{"x":[0.167],"y":[0.167]},"t":28,"s":[0]},{"i":{"x":[0.833],"y":[0.833]},"o":{"x":[0.167],"y":[0.167]},"t":32,"s":[100]},{"i":{"x":[0.833],"y":[0.833]},"o":{"x":[0.167],"y":[0.167]},"t":43,"s":[100]},{"t":47,"s":[0]}],"ix":11},"r":{"a":0,"k":0,"ix":10},"p":{"a":0,"k":[271.469,407.065,0],"ix":2},"a":{"a":0,"k":[0,0,0],"ix":1},"s":{"a":0,"k":[100,119.4,100],"ix":6}},"ao":0,"sy":[{"c":{"a":0,"k":[0,0,0,1],"ix":2},"o":{"a":0,"k":75,"ix":3},"a":{"a":0,"k":120,"ix":5},"s":{"a":0,"k":5,"ix":8},"d":{"a":0,"k":5,"ix":6},"ch":{"a":0,"k":0,"ix":7},"bm":{"a":0,"k":5,"ix":1},"no":{"a":0,"k":0,"ix":9},"lc":{"a":0,"k":1,"ix":10},"ty":1,"nm":"Drop Shadow"},{"c":{"a":0,"k":[0,0,0,1],"ix":2},"o":{"a":0,"k":75,"ix":3},"a":{"a":0,"k":120,"ix":5},"s":{"a":0,"k":5,"ix":8},"d":{"a":0,"k":5,"ix":6},"ch":{"a":0,"k":0,"ix":7},"bm":{"a":0,"k":5,"ix":1},"no":{"a":0,"k":0,"ix":9},"ty":2,"nm":"Inner Shadow"},{"c":{"a":0,"k":[1,1,0.745098039216,1],"ix":5},"o":{"a":0,"k":75,"ix":2},"s":{"a":0,"k":5,"ix":10},"r":{"a":0,"k":50,"ix":11},"ch":{"a":0,"k":0,"ix":9},"bm":{"a":0,"k":11,"ix":1},"no":{"a":0,"k":0,"ix":3},"j":{"a":0,"k":0,"ix":12},"ty":3,"nm":"Outer Glow"},{"c":{"a":0,"k":[1,1,0.745098039216,1],"ix":5},"o":{"a":0,"k":75,"ix":2},"s":{"a":0,"k":5,"ix":11},"r":{"a":0,"k":50,"ix":12},"sr":{"a":0,"k":1,"ix":9},"ch":{"a":0,"k":0,"ix":10},"bm":{"a":0,"k":11,"ix":1},"no":{"a":0,"k":0,"ix":3},"j":{"a":0,"k":0,"ix":13},"ty":4,"nm":"Inner Glow"},{"c":{"a":0,"k":[1,0,0,1],"ix":2},"s":{"a":0,"k":3,"ix":3},"ty":0,"nm":"Stroke"}],"shapes":[{"ty":"gr","it":[{"ty":"rc","d":1,"s":{"a":0,"k":[5.5,64.5],"ix":2},"p":{"a":0,"k":[0,0],"ix":3},"r":{"a":0,"k":0,"ix":4},"nm":"Rectangle Path 1","mn":"ADBE Vector Shape - Rect","hd":false},{"ty":"fl","c":{"a":0,"k":[0.721568627451,0.376470588235,0.38431372549,1],"ix":4},"o":{"a":0,"k":100,"ix":5},"r":1,"bm":1,"nm":"Fill 1","mn":"ADBE Vector Graphic - Fill","hd":false},{"ty":"tr","p":{"a":0,"k":[-72.5,-8.75],"ix":2},"a":{"a":0,"k":[0,0],"ix":1},"s":{"a":0,"k":[100,107.049],"ix":3},"r":{"a":0,"k":0,"ix":6},"o":{"a":0,"k":100,"ix":7},"sk":{"a":0,"k":0,"ix":4},"sa":{"a":0,"k":0,"ix":5},"nm":"Transform"}],"nm":"Rectangle 1","np":3,"cix":2,"bm":0,"ix":1,"mn":"ADBE Vector Group","hd":false}],"ip":0,"op":300,"st":0,"bm":0},{"ddd":0,"ind":9,"ty":4,"nm":"Shape Layer 9","sr":1,"ks":{"o":{"a":1,"k":[{"i":{"x":[0.833],"y":[0.833]},"o":{"x":[0.167],"y":[0.167]},"t":32,"s":[0]},{"i":{"x":[0.833],"y":[0.833]},"o":{"x":[0.167],"y":[0.167]},"t":36,"s":[100]},{"i":{"x":[0.833],"y":[0.833]},"o":{"x":[0.167],"y":[0.167]},"t":47,"s":[100]},{"t":51,"s":[0]}],"ix":11},"r":{"a":0,"k":0,"ix":10},"p":{"a":0,"k":[260.25,408.744,0],"ix":2},"a":{"a":0,"k":[0,0,0],"ix":1},"s":{"a":0,"k":[100,123.28,100],"ix":6}},"ao":0,"sy":[{"c":{"a":0,"k":[0,0,0,1],"ix":2},"o":{"a":0,"k":75,"ix":3},"a":{"a":0,"k":120,"ix":5},"s":{"a":0,"k":5,"ix":8},"d":{"a":0,"k":5,"ix":6},"ch":{"a":0,"k":0,"ix":7},"bm":{"a":0,"k":5,"ix":1},"no":{"a":0,"k":0,"ix":9},"lc":{"a":0,"k":1,"ix":10},"ty":1,"nm":"Drop Shadow"},{"c":{"a":0,"k":[0,0,0,1],"ix":2},"o":{"a":0,"k":75,"ix":3},"a":{"a":0,"k":120,"ix":5},"s":{"a":0,"k":5,"ix":8},"d":{"a":0,"k":5,"ix":6},"ch":{"a":0,"k":0,"ix":7},"bm":{"a":0,"k":5,"ix":1},"no":{"a":0,"k":0,"ix":9},"ty":2,"nm":"Inner Shadow"},{"c":{"a":0,"k":[1,1,0.745098039216,1],"ix":5},"o":{"a":0,"k":75,"ix":2},"s":{"a":0,"k":5,"ix":10},"r":{"a":0,"k":50,"ix":11},"ch":{"a":0,"k":0,"ix":9},"bm":{"a":0,"k":11,"ix":1},"no":{"a":0,"k":0,"ix":3},"j":{"a":0,"k":0,"ix":12},"ty":3,"nm":"Outer Glow"},{"c":{"a":0,"k":[1,1,0.745098039216,1],"ix":5},"o":{"a":0,"k":75,"ix":2},"s":{"a":0,"k":5,"ix":11},"r":{"a":0,"k":50,"ix":12},"sr":{"a":0,"k":1,"ix":9},"ch":{"a":0,"k":0,"ix":10},"bm":{"a":0,"k":11,"ix":1},"no":{"a":0,"k":0,"ix":3},"j":{"a":0,"k":0,"ix":13},"ty":4,"nm":"Inner Glow"},{"c":{"a":0,"k":[1,0,0,1],"ix":2},"s":{"a":0,"k":3,"ix":3},"ty":0,"nm":"Stroke"}],"shapes":[{"ty":"gr","it":[{"ty":"rc","d":1,"s":{"a":0,"k":[5.5,64.5],"ix":2},"p":{"a":0,"k":[0,0],"ix":3},"r":{"a":0,"k":0,"ix":4},"nm":"Rectangle Path 1","mn":"ADBE Vector Shape - Rect","hd":false},{"ty":"fl","c":{"a":0,"k":[0.635294117647,0.308927319097,0.318252084769,1],"ix":4},"o":{"a":0,"k":100,"ix":5},"r":1,"bm":1,"nm":"Fill 1","mn":"ADBE Vector Graphic - Fill","hd":false},{"ty":"tr","p":{"a":0,"k":[-72.5,-8.75],"ix":2},"a":{"a":0,"k":[0,0],"ix":1},"s":{"a":0,"k":[100,107.049],"ix":3},"r":{"a":0,"k":0,"ix":6},"o":{"a":0,"k":100,"ix":7},"sk":{"a":0,"k":0,"ix":4},"sa":{"a":0,"k":0,"ix":5},"nm":"Transform"}],"nm":"Rectangle 1","np":3,"cix":2,"bm":0,"ix":1,"mn":"ADBE Vector Group","hd":false}],"ip":0,"op":300,"st":0,"bm":0},{"ddd":0,"ind":10,"ty":4,"nm":"Shape Layer 8","sr":1,"ks":{"o":{"a":1,"k":[{"i":{"x":[0.833],"y":[0.833]},"o":{"x":[0.167],"y":[0.167]},"t":28,"s":[0]},{"i":{"x":[0.833],"y":[0.833]},"o":{"x":[0.167],"y":[0.167]},"t":32,"s":[100]},{"i":{"x":[0.833],"y":[0.833]},"o":{"x":[0.167],"y":[0.167]},"t":43,"s":[100]},{"t":47,"s":[0]}],"ix":11},"r":{"a":0,"k":0,"ix":10},"p":{"a":0,"k":[248.969,407.065,0],"ix":2},"a":{"a":0,"k":[0,0,0],"ix":1},"s":{"a":0,"k":[100,119.4,100],"ix":6}},"ao":0,"sy":[{"c":{"a":0,"k":[0,0,0,1],"ix":2},"o":{"a":0,"k":75,"ix":3},"a":{"a":0,"k":120,"ix":5},"s":{"a":0,"k":5,"ix":8},"d":{"a":0,"k":5,"ix":6},"ch":{"a":0,"k":0,"ix":7},"bm":{"a":0,"k":5,"ix":1},"no":{"a":0,"k":0,"ix":9},"lc":{"a":0,"k":1,"ix":10},"ty":1,"nm":"Drop Shadow"},{"c":{"a":0,"k":[0,0,0,1],"ix":2},"o":{"a":0,"k":75,"ix":3},"a":{"a":0,"k":120,"ix":5},"s":{"a":0,"k":5,"ix":8},"d":{"a":0,"k":5,"ix":6},"ch":{"a":0,"k":0,"ix":7},"bm":{"a":0,"k":5,"ix":1},"no":{"a":0,"k":0,"ix":9},"ty":2,"nm":"Inner Shadow"},{"c":{"a":0,"k":[1,1,0.745098039216,1],"ix":5},"o":{"a":0,"k":75,"ix":2},"s":{"a":0,"k":5,"ix":10},"r":{"a":0,"k":50,"ix":11},"ch":{"a":0,"k":0,"ix":9},"bm":{"a":0,"k":11,"ix":1},"no":{"a":0,"k":0,"ix":3},"j":{"a":0,"k":0,"ix":12},"ty":3,"nm":"Outer Glow"},{"c":{"a":0,"k":[1,1,0.745098039216,1],"ix":5},"o":{"a":0,"k":75,"ix":2},"s":{"a":0,"k":5,"ix":11},"r":{"a":0,"k":50,"ix":12},"sr":{"a":0,"k":1,"ix":9},"ch":{"a":0,"k":0,"ix":10},"bm":{"a":0,"k":11,"ix":1},"no":{"a":0,"k":0,"ix":3},"j":{"a":0,"k":0,"ix":13},"ty":4,"nm":"Inner Glow"},{"c":{"a":0,"k":[1,0,0,1],"ix":2},"s":{"a":0,"k":3,"ix":3},"ty":0,"nm":"Stroke"}],"shapes":[{"ty":"gr","it":[{"ty":"rc","d":1,"s":{"a":0,"k":[5.5,64.5],"ix":2},"p":{"a":0,"k":[0,0],"ix":3},"r":{"a":0,"k":0,"ix":4},"nm":"Rectangle Path 1","mn":"ADBE Vector Shape - Rect","hd":false},{"ty":"fl","c":{"a":0,"k":[0.721568627451,0.376470588235,0.38431372549,1],"ix":4},"o":{"a":0,"k":100,"ix":5},"r":1,"bm":1,"nm":"Fill 1","mn":"ADBE Vector Graphic - Fill","hd":false},{"ty":"tr","p":{"a":0,"k":[-72.5,-8.75],"ix":2},"a":{"a":0,"k":[0,0],"ix":1},"s":{"a":0,"k":[100,107.049],"ix":3},"r":{"a":0,"k":0,"ix":6},"o":{"a":0,"k":100,"ix":7},"sk":{"a":0,"k":0,"ix":4},"sa":{"a":0,"k":0,"ix":5},"nm":"Transform"}],"nm":"Rectangle 1","np":3,"cix":2,"bm":0,"ix":1,"mn":"ADBE Vector Group","hd":false}],"ip":0,"op":300,"st":0,"bm":0},{"ddd":0,"ind":11,"ty":4,"nm":"Shape Layer 7","sr":1,"ks":{"o":{"a":1,"k":[{"i":{"x":[0.833],"y":[0.833]},"o":{"x":[0.167],"y":[0.167]},"t":24,"s":[0]},{"i":{"x":[0.833],"y":[0.833]},"o":{"x":[0.167],"y":[0.167]},"t":28,"s":[100]},{"i":{"x":[0.833],"y":[0.833]},"o":{"x":[0.167],"y":[0.167]},"t":39,"s":[100]},{"t":43,"s":[0]}],"ix":11},"r":{"a":0,"k":0,"ix":10},"p":{"a":0,"k":[237.688,405.805,0],"ix":2},"a":{"a":0,"k":[0,0,0],"ix":1},"s":{"a":0,"k":[100,116.49,100],"ix":6}},"ao":0,"sy":[{"c":{"a":0,"k":[0,0,0,1],"ix":2},"o":{"a":0,"k":75,"ix":3},"a":{"a":0,"k":120,"ix":5},"s":{"a":0,"k":5,"ix":8},"d":{"a":0,"k":5,"ix":6},"ch":{"a":0,"k":0,"ix":7},"bm":{"a":0,"k":5,"ix":1},"no":{"a":0,"k":0,"ix":9},"lc":{"a":0,"k":1,"ix":10},"ty":1,"nm":"Drop Shadow"},{"c":{"a":0,"k":[0,0,0,1],"ix":2},"o":{"a":0,"k":75,"ix":3},"a":{"a":0,"k":120,"ix":5},"s":{"a":0,"k":5,"ix":8},"d":{"a":0,"k":5,"ix":6},"ch":{"a":0,"k":0,"ix":7},"bm":{"a":0,"k":5,"ix":1},"no":{"a":0,"k":0,"ix":9},"ty":2,"nm":"Inner Shadow"},{"c":{"a":0,"k":[1,1,0.745098039216,1],"ix":5},"o":{"a":0,"k":75,"ix":2},"s":{"a":0,"k":5,"ix":10},"r":{"a":0,"k":50,"ix":11},"ch":{"a":0,"k":0,"ix":9},"bm":{"a":0,"k":11,"ix":1},"no":{"a":0,"k":0,"ix":3},"j":{"a":0,"k":0,"ix":12},"ty":3,"nm":"Outer Glow"},{"c":{"a":0,"k":[1,1,0.745098039216,1],"ix":5},"o":{"a":0,"k":75,"ix":2},"s":{"a":0,"k":5,"ix":11},"r":{"a":0,"k":50,"ix":12},"sr":{"a":0,"k":1,"ix":9},"ch":{"a":0,"k":0,"ix":10},"bm":{"a":0,"k":11,"ix":1},"no":{"a":0,"k":0,"ix":3},"j":{"a":0,"k":0,"ix":13},"ty":4,"nm":"Inner Glow"},{"c":{"a":0,"k":[1,0,0,1],"ix":2},"s":{"a":0,"k":3,"ix":3},"ty":0,"nm":"Stroke"}],"shapes":[{"ty":"gr","it":[{"ty":"rc","d":1,"s":{"a":0,"k":[5.5,64.5],"ix":2},"p":{"a":0,"k":[0,0],"ix":3},"r":{"a":0,"k":0,"ix":4},"nm":"Rectangle Path 1","mn":"ADBE Vector Shape - Rect","hd":false},{"ty":"fl","c":{"a":0,"k":[0.721568627451,0.376470588235,0.38431372549,1],"ix":4},"o":{"a":0,"k":100,"ix":5},"r":1,"bm":1,"nm":"Fill 1","mn":"ADBE Vector Graphic - Fill","hd":false},{"ty":"tr","p":{"a":0,"k":[-72.5,-8.75],"ix":2},"a":{"a":0,"k":[0,0],"ix":1},"s":{"a":0,"k":[100,107.049],"ix":3},"r":{"a":0,"k":0,"ix":6},"o":{"a":0,"k":100,"ix":7},"sk":{"a":0,"k":0,"ix":4},"sa":{"a":0,"k":0,"ix":5},"nm":"Transform"}],"nm":"Rectangle 1","np":3,"cix":2,"bm":0,"ix":1,"mn":"ADBE Vector Group","hd":false}],"ip":0,"op":300,"st":0,"bm":0},{"ddd":0,"ind":12,"ty":4,"nm":"Shape Layer 6","sr":1,"ks":{"o":{"a":1,"k":[{"i":{"x":[0.833],"y":[0.833]},"o":{"x":[0.167],"y":[0.167]},"t":20,"s":[0]},{"i":{"x":[0.833],"y":[0.833]},"o":{"x":[0.167],"y":[0.167]},"t":24,"s":[100]},{"i":{"x":[0.833],"y":[0.833]},"o":{"x":[0.167],"y":[0.167]},"t":35,"s":[100]},{"t":39,"s":[0]}],"ix":11},"r":{"a":0,"k":0,"ix":10},"p":{"a":0,"k":[226.406,403.707,0],"ix":2},"a":{"a":0,"k":[0,0,0],"ix":1},"s":{"a":0,"k":[100,111.64,100],"ix":6}},"ao":0,"sy":[{"c":{"a":0,"k":[0,0,0,1],"ix":2},"o":{"a":0,"k":75,"ix":3},"a":{"a":0,"k":120,"ix":5},"s":{"a":0,"k":5,"ix":8},"d":{"a":0,"k":5,"ix":6},"ch":{"a":0,"k":0,"ix":7},"bm":{"a":0,"k":5,"ix":1},"no":{"a":0,"k":0,"ix":9},"lc":{"a":0,"k":1,"ix":10},"ty":1,"nm":"Drop Shadow"},{"c":{"a":0,"k":[0,0,0,1],"ix":2},"o":{"a":0,"k":75,"ix":3},"a":{"a":0,"k":120,"ix":5},"s":{"a":0,"k":5,"ix":8},"d":{"a":0,"k":5,"ix":6},"ch":{"a":0,"k":0,"ix":7},"bm":{"a":0,"k":5,"ix":1},"no":{"a":0,"k":0,"ix":9},"ty":2,"nm":"Inner Shadow"},{"c":{"a":0,"k":[1,1,0.745098039216,1],"ix":5},"o":{"a":0,"k":75,"ix":2},"s":{"a":0,"k":5,"ix":10},"r":{"a":0,"k":50,"ix":11},"ch":{"a":0,"k":0,"ix":9},"bm":{"a":0,"k":11,"ix":1},"no":{"a":0,"k":0,"ix":3},"j":{"a":0,"k":0,"ix":12},"ty":3,"nm":"Outer Glow"},{"c":{"a":0,"k":[1,1,0.745098039216,1],"ix":5},"o":{"a":0,"k":75,"ix":2},"s":{"a":0,"k":5,"ix":11},"r":{"a":0,"k":50,"ix":12},"sr":{"a":0,"k":1,"ix":9},"ch":{"a":0,"k":0,"ix":10},"bm":{"a":0,"k":11,"ix":1},"no":{"a":0,"k":0,"ix":3},"j":{"a":0,"k":0,"ix":13},"ty":4,"nm":"Inner Glow"},{"c":{"a":0,"k":[1,0,0,1],"ix":2},"s":{"a":0,"k":3,"ix":3},"ty":0,"nm":"Stroke"}],"shapes":[{"ty":"gr","it":[{"ty":"rc","d":1,"s":{"a":0,"k":[5.5,64.5],"ix":2},"p":{"a":0,"k":[0,0],"ix":3},"r":{"a":0,"k":0,"ix":4},"nm":"Rectangle Path 1","mn":"ADBE Vector Shape - Rect","hd":false},{"ty":"fl","c":{"a":0,"k":[0.721568627451,0.376470588235,0.38431372549,1],"ix":4},"o":{"a":0,"k":100,"ix":5},"r":1,"bm":1,"nm":"Fill 1","mn":"ADBE Vector Graphic - Fill","hd":false},{"ty":"tr","p":{"a":0,"k":[-72.5,-8.75],"ix":2},"a":{"a":0,"k":[0,0],"ix":1},"s":{"a":0,"k":[100,107.049],"ix":3},"r":{"a":0,"k":0,"ix":6},"o":{"a":0,"k":100,"ix":7},"sk":{"a":0,"k":0,"ix":4},"sa":{"a":0,"k":0,"ix":5},"nm":"Transform"}],"nm":"Rectangle 1","np":3,"cix":2,"bm":0,"ix":1,"mn":"ADBE Vector Group","hd":false}],"ip":0,"op":300,"st":0,"bm":0},{"ddd":0,"ind":13,"ty":4,"nm":"Shape Layer 5","sr":1,"ks":{"o":{"a":1,"k":[{"i":{"x":[0.833],"y":[0.833]},"o":{"x":[0.167],"y":[0.167]},"t":16,"s":[0]},{"i":{"x":[0.833],"y":[0.833]},"o":{"x":[0.167],"y":[0.167]},"t":20,"s":[100]},{"i":{"x":[0.833],"y":[0.833]},"o":{"x":[0.167],"y":[0.167]},"t":31,"s":[100]},{"t":35,"s":[0]}],"ix":11},"r":{"a":0,"k":0,"ix":10},"p":{"a":0,"k":[215.125,402.447,0],"ix":2},"a":{"a":0,"k":[0,0,0],"ix":1},"s":{"a":0,"k":[100,108.73,100],"ix":6}},"ao":0,"sy":[{"c":{"a":0,"k":[0,0,0,1],"ix":2},"o":{"a":0,"k":75,"ix":3},"a":{"a":0,"k":120,"ix":5},"s":{"a":0,"k":5,"ix":8},"d":{"a":0,"k":5,"ix":6},"ch":{"a":0,"k":0,"ix":7},"bm":{"a":0,"k":5,"ix":1},"no":{"a":0,"k":0,"ix":9},"lc":{"a":0,"k":1,"ix":10},"ty":1,"nm":"Drop Shadow"},{"c":{"a":0,"k":[0,0,0,1],"ix":2},"o":{"a":0,"k":75,"ix":3},"a":{"a":0,"k":120,"ix":5},"s":{"a":0,"k":5,"ix":8},"d":{"a":0,"k":5,"ix":6},"ch":{"a":0,"k":0,"ix":7},"bm":{"a":0,"k":5,"ix":1},"no":{"a":0,"k":0,"ix":9},"ty":2,"nm":"Inner Shadow"},{"c":{"a":0,"k":[1,1,0.745098039216,1],"ix":5},"o":{"a":0,"k":75,"ix":2},"s":{"a":0,"k":5,"ix":10},"r":{"a":0,"k":50,"ix":11},"ch":{"a":0,"k":0,"ix":9},"bm":{"a":0,"k":11,"ix":1},"no":{"a":0,"k":0,"ix":3},"j":{"a":0,"k":0,"ix":12},"ty":3,"nm":"Outer Glow"},{"c":{"a":0,"k":[1,1,0.745098039216,1],"ix":5},"o":{"a":0,"k":75,"ix":2},"s":{"a":0,"k":5,"ix":11},"r":{"a":0,"k":50,"ix":12},"sr":{"a":0,"k":1,"ix":9},"ch":{"a":0,"k":0,"ix":10},"bm":{"a":0,"k":11,"ix":1},"no":{"a":0,"k":0,"ix":3},"j":{"a":0,"k":0,"ix":13},"ty":4,"nm":"Inner Glow"},{"c":{"a":0,"k":[1,0,0,1],"ix":2},"s":{"a":0,"k":3,"ix":3},"ty":0,"nm":"Stroke"}],"shapes":[{"ty":"gr","it":[{"ty":"rc","d":1,"s":{"a":0,"k":[5.5,64.5],"ix":2},"p":{"a":0,"k":[0,0],"ix":3},"r":{"a":0,"k":0,"ix":4},"nm":"Rectangle Path 1","mn":"ADBE Vector Shape - Rect","hd":false},{"ty":"fl","c":{"a":0,"k":[0.721568627451,0.376470588235,0.38431372549,1],"ix":4},"o":{"a":0,"k":100,"ix":5},"r":1,"bm":1,"nm":"Fill 1","mn":"ADBE Vector Graphic - Fill","hd":false},{"ty":"tr","p":{"a":0,"k":[-72.5,-8.75],"ix":2},"a":{"a":0,"k":[0,0],"ix":1},"s":{"a":0,"k":[100,107.049],"ix":3},"r":{"a":0,"k":0,"ix":6},"o":{"a":0,"k":100,"ix":7},"sk":{"a":0,"k":0,"ix":4},"sa":{"a":0,"k":0,"ix":5},"nm":"Transform"}],"nm":"Rectangle 1","np":3,"cix":2,"bm":0,"ix":1,"mn":"ADBE Vector Group","hd":false}],"ip":0,"op":300,"st":0,"bm":0},{"ddd":0,"ind":14,"ty":4,"nm":"Shape Layer 4","sr":1,"ks":{"o":{"a":1,"k":[{"i":{"x":[0.833],"y":[0.833]},"o":{"x":[0.167],"y":[0.167]},"t":12,"s":[0]},{"i":{"x":[0.833],"y":[0.833]},"o":{"x":[0.167],"y":[0.167]},"t":16,"s":[100]},{"i":{"x":[0.833],"y":[0.833]},"o":{"x":[0.167],"y":[0.167]},"t":27,"s":[100]},{"t":31,"s":[0]}],"ix":11},"r":{"a":0,"k":0,"ix":10},"p":{"a":0,"k":[203.844,401.188,0],"ix":2},"a":{"a":0,"k":[0,0,0],"ix":1},"s":{"a":0,"k":[100,105.82,100],"ix":6}},"ao":0,"sy":[{"c":{"a":0,"k":[0,0,0,1],"ix":2},"o":{"a":0,"k":75,"ix":3},"a":{"a":0,"k":120,"ix":5},"s":{"a":0,"k":5,"ix":8},"d":{"a":0,"k":5,"ix":6},"ch":{"a":0,"k":0,"ix":7},"bm":{"a":0,"k":5,"ix":1},"no":{"a":0,"k":0,"ix":9},"lc":{"a":0,"k":1,"ix":10},"ty":1,"nm":"Drop Shadow"},{"c":{"a":0,"k":[0,0,0,1],"ix":2},"o":{"a":0,"k":75,"ix":3},"a":{"a":0,"k":120,"ix":5},"s":{"a":0,"k":5,"ix":8},"d":{"a":0,"k":5,"ix":6},"ch":{"a":0,"k":0,"ix":7},"bm":{"a":0,"k":5,"ix":1},"no":{"a":0,"k":0,"ix":9},"ty":2,"nm":"Inner Shadow"},{"c":{"a":0,"k":[1,1,0.745098039216,1],"ix":5},"o":{"a":0,"k":75,"ix":2},"s":{"a":0,"k":5,"ix":10},"r":{"a":0,"k":50,"ix":11},"ch":{"a":0,"k":0,"ix":9},"bm":{"a":0,"k":11,"ix":1},"no":{"a":0,"k":0,"ix":3},"j":{"a":0,"k":0,"ix":12},"ty":3,"nm":"Outer Glow"},{"c":{"a":0,"k":[1,1,0.745098039216,1],"ix":5},"o":{"a":0,"k":75,"ix":2},"s":{"a":0,"k":5,"ix":11},"r":{"a":0,"k":50,"ix":12},"sr":{"a":0,"k":1,"ix":9},"ch":{"a":0,"k":0,"ix":10},"bm":{"a":0,"k":11,"ix":1},"no":{"a":0,"k":0,"ix":3},"j":{"a":0,"k":0,"ix":13},"ty":4,"nm":"Inner Glow"},{"c":{"a":0,"k":[1,0,0,1],"ix":2},"s":{"a":0,"k":3,"ix":3},"ty":0,"nm":"Stroke"}],"shapes":[{"ty":"gr","it":[{"ty":"rc","d":1,"s":{"a":0,"k":[5.5,64.5],"ix":2},"p":{"a":0,"k":[0,0],"ix":3},"r":{"a":0,"k":0,"ix":4},"nm":"Rectangle Path 1","mn":"ADBE Vector Shape - Rect","hd":false},{"ty":"fl","c":{"a":0,"k":[0.733333333333,0.458823529412,0.466666666667,1],"ix":4},"o":{"a":0,"k":100,"ix":5},"r":1,"bm":1,"nm":"Fill 1","mn":"ADBE Vector Graphic - Fill","hd":false},{"ty":"tr","p":{"a":0,"k":[-72.5,-8.75],"ix":2},"a":{"a":0,"k":[0,0],"ix":1},"s":{"a":0,"k":[100,107.049],"ix":3},"r":{"a":0,"k":0,"ix":6},"o":{"a":0,"k":100,"ix":7},"sk":{"a":0,"k":0,"ix":4},"sa":{"a":0,"k":0,"ix":5},"nm":"Transform"}],"nm":"Rectangle 1","np":3,"cix":2,"bm":0,"ix":1,"mn":"ADBE Vector Group","hd":false}],"ip":-9,"op":291,"st":-9,"bm":0},{"ddd":0,"ind":15,"ty":4,"nm":"Shape Layer 3","sr":1,"ks":{"o":{"a":1,"k":[{"i":{"x":[0.833],"y":[0.833]},"o":{"x":[0.167],"y":[0.167]},"t":8,"s":[0]},{"i":{"x":[0.833],"y":[0.833]},"o":{"x":[0.167],"y":[0.167]},"t":12,"s":[100]},{"i":{"x":[0.833],"y":[0.833]},"o":{"x":[0.167],"y":[0.167]},"t":23,"s":[100]},{"t":27,"s":[0]}],"ix":11},"r":{"a":0,"k":0,"ix":10},"p":{"a":0,"k":[192.563,399.509,0],"ix":2},"a":{"a":0,"k":[0,0,0],"ix":1},"s":{"a":0,"k":[100,101.94,100],"ix":6}},"ao":0,"sy":[{"c":{"a":0,"k":[0,0,0,1],"ix":2},"o":{"a":0,"k":75,"ix":3},"a":{"a":0,"k":120,"ix":5},"s":{"a":0,"k":5,"ix":8},"d":{"a":0,"k":5,"ix":6},"ch":{"a":0,"k":0,"ix":7},"bm":{"a":0,"k":5,"ix":1},"no":{"a":0,"k":0,"ix":9},"lc":{"a":0,"k":1,"ix":10},"ty":1,"nm":"Drop Shadow"},{"c":{"a":0,"k":[0,0,0,1],"ix":2},"o":{"a":0,"k":75,"ix":3},"a":{"a":0,"k":120,"ix":5},"s":{"a":0,"k":5,"ix":8},"d":{"a":0,"k":5,"ix":6},"ch":{"a":0,"k":0,"ix":7},"bm":{"a":0,"k":5,"ix":1},"no":{"a":0,"k":0,"ix":9},"ty":2,"nm":"Inner Shadow"},{"c":{"a":0,"k":[1,1,0.745098039216,1],"ix":5},"o":{"a":0,"k":75,"ix":2},"s":{"a":0,"k":5,"ix":10},"r":{"a":0,"k":50,"ix":11},"ch":{"a":0,"k":0,"ix":9},"bm":{"a":0,"k":11,"ix":1},"no":{"a":0,"k":0,"ix":3},"j":{"a":0,"k":0,"ix":12},"ty":3,"nm":"Outer Glow"},{"c":{"a":0,"k":[1,1,0.745098039216,1],"ix":5},"o":{"a":0,"k":75,"ix":2},"s":{"a":0,"k":5,"ix":11},"r":{"a":0,"k":50,"ix":12},"sr":{"a":0,"k":1,"ix":9},"ch":{"a":0,"k":0,"ix":10},"bm":{"a":0,"k":11,"ix":1},"no":{"a":0,"k":0,"ix":3},"j":{"a":0,"k":0,"ix":13},"ty":4,"nm":"Inner Glow"},{"c":{"a":0,"k":[1,0,0,1],"ix":2},"s":{"a":0,"k":3,"ix":3},"ty":0,"nm":"Stroke"}],"shapes":[{"ty":"gr","it":[{"ty":"rc","d":1,"s":{"a":0,"k":[5.5,64.5],"ix":2},"p":{"a":0,"k":[0,0],"ix":3},"r":{"a":0,"k":0,"ix":4},"nm":"Rectangle Path 1","mn":"ADBE Vector Shape - Rect","hd":false},{"ty":"fl","c":{"a":0,"k":[0.733333333333,0.458823529412,0.466666666667,1],"ix":4},"o":{"a":0,"k":100,"ix":5},"r":1,"bm":1,"nm":"Fill 1","mn":"ADBE Vector Graphic - Fill","hd":false},{"ty":"tr","p":{"a":0,"k":[-72.5,-8.75],"ix":2},"a":{"a":0,"k":[0,0],"ix":1},"s":{"a":0,"k":[100,107.049],"ix":3},"r":{"a":0,"k":0,"ix":6},"o":{"a":0,"k":100,"ix":7},"sk":{"a":0,"k":0,"ix":4},"sa":{"a":0,"k":0,"ix":5},"nm":"Transform"}],"nm":"Rectangle 1","np":3,"cix":2,"bm":0,"ix":1,"mn":"ADBE Vector Group","hd":false}],"ip":-5,"op":295,"st":-5,"bm":0},{"ddd":0,"ind":16,"ty":4,"nm":"Shape Layer 2","sr":1,"ks":{"o":{"a":1,"k":[{"i":{"x":[0.833],"y":[0.833]},"o":{"x":[0.167],"y":[0.167]},"t":4,"s":[0]},{"i":{"x":[0.833],"y":[0.833]},"o":{"x":[0.167],"y":[0.167]},"t":8,"s":[100]},{"i":{"x":[0.833],"y":[0.833]},"o":{"x":[0.167],"y":[0.167]},"t":19,"s":[100]},{"t":23,"s":[0]}],"ix":11},"r":{"a":0,"k":0,"ix":10},"p":{"a":0,"k":[181.281,397.411,0],"ix":2},"a":{"a":0,"k":[0,0,0],"ix":1},"s":{"a":0,"k":[100,97.09,100],"ix":6}},"ao":0,"sy":[{"c":{"a":0,"k":[0,0,0,1],"ix":2},"o":{"a":0,"k":75,"ix":3},"a":{"a":0,"k":120,"ix":5},"s":{"a":0,"k":5,"ix":8},"d":{"a":0,"k":5,"ix":6},"ch":{"a":0,"k":0,"ix":7},"bm":{"a":0,"k":5,"ix":1},"no":{"a":0,"k":0,"ix":9},"lc":{"a":0,"k":1,"ix":10},"ty":1,"nm":"Drop Shadow"},{"c":{"a":0,"k":[0,0,0,1],"ix":2},"o":{"a":0,"k":75,"ix":3},"a":{"a":0,"k":120,"ix":5},"s":{"a":0,"k":5,"ix":8},"d":{"a":0,"k":5,"ix":6},"ch":{"a":0,"k":0,"ix":7},"bm":{"a":0,"k":5,"ix":1},"no":{"a":0,"k":0,"ix":9},"ty":2,"nm":"Inner Shadow"},{"c":{"a":0,"k":[1,1,0.745098039216,1],"ix":5},"o":{"a":0,"k":75,"ix":2},"s":{"a":0,"k":5,"ix":10},"r":{"a":0,"k":50,"ix":11},"ch":{"a":0,"k":0,"ix":9},"bm":{"a":0,"k":11,"ix":1},"no":{"a":0,"k":0,"ix":3},"j":{"a":0,"k":0,"ix":12},"ty":3,"nm":"Outer Glow"},{"c":{"a":0,"k":[1,1,0.745098039216,1],"ix":5},"o":{"a":0,"k":75,"ix":2},"s":{"a":0,"k":5,"ix":11},"r":{"a":0,"k":50,"ix":12},"sr":{"a":0,"k":1,"ix":9},"ch":{"a":0,"k":0,"ix":10},"bm":{"a":0,"k":11,"ix":1},"no":{"a":0,"k":0,"ix":3},"j":{"a":0,"k":0,"ix":13},"ty":4,"nm":"Inner Glow"},{"c":{"a":0,"k":[1,0,0,1],"ix":2},"s":{"a":0,"k":3,"ix":3},"ty":0,"nm":"Stroke"}],"shapes":[{"ty":"gr","it":[{"ty":"rc","d":1,"s":{"a":0,"k":[5.5,64.5],"ix":2},"p":{"a":0,"k":[0,0],"ix":3},"r":{"a":0,"k":0,"ix":4},"nm":"Rectangle Path 1","mn":"ADBE Vector Shape - Rect","hd":false},{"ty":"fl","c":{"a":0,"k":[0.733333333333,0.458823529412,0.466666666667,1],"ix":4},"o":{"a":0,"k":100,"ix":5},"r":1,"bm":1,"nm":"Fill 1","mn":"ADBE Vector Graphic - Fill","hd":false},{"ty":"tr","p":{"a":0,"k":[-72.5,-8.75],"ix":2},"a":{"a":0,"k":[0,0],"ix":1},"s":{"a":0,"k":[100,107.049],"ix":3},"r":{"a":0,"k":0,"ix":6},"o":{"a":0,"k":100,"ix":7},"sk":{"a":0,"k":0,"ix":4},"sa":{"a":0,"k":0,"ix":5},"nm":"Transform"}],"nm":"Rectangle 1","np":3,"cix":2,"bm":0,"ix":1,"mn":"ADBE Vector Group","hd":false}],"ip":-4,"op":296,"st":-4,"bm":0},{"ddd":0,"ind":17,"ty":4,"nm":"Shape Layer 1","sr":1,"ks":{"o":{"a":1,"k":[{"i":{"x":[0.833],"y":[0.833]},"o":{"x":[0.167],"y":[0.167]},"t":0,"s":[0]},{"i":{"x":[0.833],"y":[0.833]},"o":{"x":[0.167],"y":[0.167]},"t":4,"s":[100]},{"i":{"x":[0.833],"y":[0.833]},"o":{"x":[0.167],"y":[0.167]},"t":15,"s":[100]},{"t":19,"s":[0]}],"ix":11},"r":{"a":0,"k":0,"ix":10},"p":{"a":0,"k":[170,396.571,0],"ix":2},"a":{"a":0,"k":[0,0,0],"ix":1},"s":{"a":0,"k":[100,95.15,100],"ix":6}},"ao":0,"sy":[{"c":{"a":0,"k":[0,0,0,1],"ix":2},"o":{"a":0,"k":75,"ix":3},"a":{"a":0,"k":120,"ix":5},"s":{"a":0,"k":5,"ix":8},"d":{"a":0,"k":5,"ix":6},"ch":{"a":0,"k":0,"ix":7},"bm":{"a":0,"k":5,"ix":1},"no":{"a":0,"k":0,"ix":9},"lc":{"a":0,"k":1,"ix":10},"ty":1,"nm":"Drop Shadow"},{"c":{"a":0,"k":[0,0,0,1],"ix":2},"o":{"a":0,"k":75,"ix":3},"a":{"a":0,"k":120,"ix":5},"s":{"a":0,"k":5,"ix":8},"d":{"a":0,"k":5,"ix":6},"ch":{"a":0,"k":0,"ix":7},"bm":{"a":0,"k":5,"ix":1},"no":{"a":0,"k":0,"ix":9},"ty":2,"nm":"Inner Shadow"},{"c":{"a":0,"k":[1,1,0.745098039216,1],"ix":5},"o":{"a":0,"k":75,"ix":2},"s":{"a":0,"k":5,"ix":10},"r":{"a":0,"k":50,"ix":11},"ch":{"a":0,"k":0,"ix":9},"bm":{"a":0,"k":11,"ix":1},"no":{"a":0,"k":0,"ix":3},"j":{"a":0,"k":0,"ix":12},"ty":3,"nm":"Outer Glow"},{"c":{"a":0,"k":[1,1,0.745098039216,1],"ix":5},"o":{"a":0,"k":75,"ix":2},"s":{"a":0,"k":5,"ix":11},"r":{"a":0,"k":50,"ix":12},"sr":{"a":0,"k":1,"ix":9},"ch":{"a":0,"k":0,"ix":10},"bm":{"a":0,"k":11,"ix":1},"no":{"a":0,"k":0,"ix":3},"j":{"a":0,"k":0,"ix":13},"ty":4,"nm":"Inner Glow"},{"c":{"a":0,"k":[1,0,0,1],"ix":2},"s":{"a":0,"k":3,"ix":3},"ty":0,"nm":"Stroke"}],"shapes":[{"ty":"gr","it":[{"ty":"rc","d":1,"s":{"a":0,"k":[5.5,64.5],"ix":2},"p":{"a":0,"k":[0,0],"ix":3},"r":{"a":0,"k":0,"ix":4},"nm":"Rectangle Path 1","mn":"ADBE Vector Shape - Rect","hd":false},{"ty":"fl","c":{"a":0,"k":[0.733333333333,0.458823529412,0.466666666667,1],"ix":4},"o":{"a":0,"k":100,"ix":5},"r":1,"bm":1,"nm":"Fill 1","mn":"ADBE Vector Graphic - Fill","hd":false},{"ty":"tr","p":{"a":0,"k":[-72.5,-8.75],"ix":2},"a":{"a":0,"k":[0,0],"ix":1},"s":{"a":0,"k":[100,107.049],"ix":3},"r":{"a":0,"k":0,"ix":6},"o":{"a":0,"k":100,"ix":7},"sk":{"a":0,"k":0,"ix":4},"sa":{"a":0,"k":0,"ix":5},"nm":"Transform"}],"nm":"Rectangle 1","np":3,"cix":2,"bm":0,"ix":1,"mn":"ADBE Vector Group","hd":false}],"ip":0,"op":300,"st":0,"bm":0}],"markers":[]}